addit/__init__.py
addit/addit.py
addit-0.3.0.dist-info/LICENSE
addit-0.3.0.dist-info/METADATA
addit-0.3.0.dist-info/WHEEL
addit-0.3.0.dist-info/entry_points.txt
addit-0.3.0.dist-info/top_level.txt
addit-0.3.0.dist-info/RECORD
